video_effects/__init__.py
video_effects/glitch.py
video_effects/panning.py
video_effects/shake.py
video_effects/sway.py
video_effects/zoom_pan.py
video_effects-0.0.2.dist-info/METADATA
video_effects-0.0.2.dist-info/WHEEL
video_effects-0.0.2.dist-info/top_level.txt
video_effects-0.0.2.dist-info/RECORD
